{
  "videos": [
    {
      "id": "KFqmykBHieI",
      "duration": 4301,
      "start_time": 0
    },
    {
      "id": "ojZtQgYbyZA",
      "duration": 3635,
      "start_time": 4301
    },
    {
      "id": "ZKC-5HHORpA",
      "duration": 5578,
      "start_time": 7936
    },
    {
      "id": "THHHtf1c0gY",
      "duration": 5334,
      "start_time": 13514
    },
    {
      "id": "9qWP6WjJd1Q",
      "duration": 5181,
      "start_time": 18848
    },
    {
      "id": "oeiWhX6TgAc",
      "duration": 6400,
      "start_time": 24029
    },
    {
      "id": "m_m4YKnWjdg",
      "duration": 8697,
      "start_time": 30429
    },
    {
      "id": "X5LjKl7pkqM",
      "duration": 8244,
      "start_time": 39126
    },
    {
      "id": "RoXtGILD2VI",
      "duration": 4858,
      "start_time": 47370
    },
    {
      "id": "YP2gId2xO-Q",
      "duration": 5312,
      "start_time": 52228
    },
    {
      "id": "QDBLq1QPdeM",
      "duration": 5949,
      "start_time": 57540
    },
    {
      "id": "_7Q62_zkiDU",
      "duration": 5417,
      "start_time": 63489
    },
    {
      "id": "OWFPaM4ap50",
      "duration": 7270,
      "start_time": 68906
    },
    {
      "id": "3Xg3UBwZ7R4",
      "duration": 6148,
      "start_time": 76176
    },
    {
      "id": "kWcRw1OJWWY",
      "duration": 5783,
      "start_time": 82324
    },
    {
      "id": "DC6yfy0w-Gw",
      "duration": 5202,
      "start_time": 88107
    },
    {
      "id": "S2dR_GtQ86M",
      "duration": 5155,
      "start_time": 93309
    },
    {
      "id": "JWHUvI_Y1ro",
      "duration": 6036,
      "start_time": 98464
    },
    {
      "id": "_Jxsig6eHi0",
      "duration": 4888,
      "start_time": 104500
    },
    {
      "id": "bp3mDy9VEIE",
      "duration": 5154,
      "start_time": 109388
    },
    {
      "id": "MWgOlSLHYfI",
      "duration": 4885,
      "start_time": 114542
    },
    {
      "id": "eOrGgFDoNJ4",
      "duration": 8114,
      "start_time": 119427
    },
    {
      "id": "kcU0zG0_8YI",
      "duration": 5006,
      "start_time": 127541
    },
    {
      "id": "EzMeJvoePfo",
      "duration": 5997,
      "start_time": 132547
    },
    {
      "id": "2cCybZNS2J4",
      "duration": 5702,
      "start_time": 138544
    },
    {
      "id": "L72C_kKiEZA",
      "duration": 4737,
      "start_time": 144246
    },
    {
      "id": "lp886PX6dBM",
      "duration": 3891,
      "start_time": 148983
    },
    {
      "id": "4k7JA5Fp0OI",
      "duration": 6159,
      "start_time": 152874
    },
    {
      "id": "YwfIs_zkvgc",
      "duration": 3771,
      "start_time": 159033
    },
    {
      "id": "bNxXUAbryYE",
      "duration": 3831,
      "start_time": 162804
    },
    {
      "id": "GvQalEZLsf0",
      "duration": 7378,
      "start_time": 166635
    },
    {
      "id": "6knlL4-BdTA",
      "duration": 4940,
      "start_time": 174013
    },
    {
      "id": "yrFGw4vj9d4",
      "duration": 6773,
      "start_time": 178953
    },
    {
      "id": "s9lncUek9HY",
      "duration": 4962,
      "start_time": 185726
    },
    {
      "id": "E4NSUKiQSec",
      "duration": 4983,
      "start_time": 190688
    },
    {
      "id": "9rZeDI9jDYU",
      "duration": 6407,
      "start_time": 195671
    },
    {
      "id": "mgnHfBLhy5k",
      "duration": 6066,
      "start_time": 202078
    },
    {
      "id": "Bg4XLWXA8pQ",
      "duration": 5701,
      "start_time": 208144
    },
    {
      "id": "jLSwK7m_hvw",
      "duration": 5144,
      "start_time": 213845
    },
    {
      "id": "LSB24QHnXOM",
      "duration": 4722,
      "start_time": 218989
    },
    {
      "id": "nqy6xNWddA4",
      "duration": 4179,
      "start_time": 223711
    },
    {
      "id": "4JXebp02BCQ",
      "duration": 3539,
      "start_time": 227890
    },
    {
      "id": "eWV0TQ7xMOk",
      "duration": 3743,
      "start_time": 231429
    },
    {
      "id": "laoklyJsRv0",
      "duration": 4444,
      "start_time": 235172
    },
    {
      "id": "OYNO75mdYvA",
      "duration": 5642,
      "start_time": 239616
    },
    {
      "id": "6oH8QlWgkSU",
      "duration": 5890,
      "start_time": 245258
    },
    {
      "id": "50srUwXkWuc",
      "duration": 5196,
      "start_time": 251148
    },
    {
      "id": "UaywM8HS1n4",
      "duration": 4489,
      "start_time": 256344
    },
    {
      "id": "LkeqO0tkJzA",
      "duration": 6104,
      "start_time": 260833
    },
    {
      "id": "jQAZ8D8q5ss",
      "duration": 5375,
      "start_time": 266937
    },
    {
      "id": "SYT9pTLSMJ8",
      "duration": 4605,
      "start_time": 272312
    },
    {
      "id": "bJ5LPke48g4",
      "duration": 5326,
      "start_time": 276917
    },
    {
      "id": "9jpv0Pr7hhw",
      "duration": 5005,
      "start_time": 282243
    },
    {
      "id": "H_TmJ-fV59Y",
      "duration": 5443,
      "start_time": 287248
    },
    {
      "id": "BuvV2OdTfdU",
      "duration": 6370,
      "start_time": 292691
    },
    {
      "id": "eUZby5yBYCE",
      "duration": 4774,
      "start_time": 299061
    },
    {
      "id": "1Cbyq-ta5kw",
      "duration": 5644,
      "start_time": 303835
    },
    {
      "id": "gfdsTte2FPg",
      "duration": 4213,
      "start_time": 309479
    },
    {
      "id": "6niUDdul4Lk",
      "duration": 5489,
      "start_time": 313692
    },
    {
      "id": "dFqr71bttrc",
      "duration": 5630,
      "start_time": 319181
    },
    {
      "id": "Y4iV-7lY5qY",
      "duration": 5019,
      "start_time": 324811
    },
    {
      "id": "LcYxpyqjCyQ",
      "duration": 5561,
      "start_time": 329830
    },
    {
      "id": "hrCFEq6mVY8",
      "duration": 10617,
      "start_time": 335391
    },
    {
      "id": "1o9SskdQWzw",
      "duration": 6618,
      "start_time": 346008
    },
    {
      "id": "8xR14Hp3Vig",
      "duration": 5045,
      "start_time": 352626
    },
    {
      "id": "E5p5ylKYk_o",
      "duration": 4210,
      "start_time": 357671
    },
    {
      "id": "wfvLpa9LfVk",
      "duration": 5718,
      "start_time": 361881
    },
    {
      "id": "gtxxKfG1PV4",
      "duration": 5980,
      "start_time": 367599
    },
    {
      "id": "JP678wdm7Tk",
      "duration": 6102,
      "start_time": 373579
    },
    {
      "id": "f8IZGi_SSjc",
      "duration": 5271,
      "start_time": 379681
    },
    {
      "id": "yUB9J2ZMczw",
      "duration": 7733,
      "start_time": 384952
    },
    {
      "id": "fUrt2zVNlzA",
      "duration": 7904,
      "start_time": 392685
    },
    {
      "id": "JkIokIoovNU",
      "duration": 5619,
      "start_time": 400589
    },
    {
      "id": "EHqWCrcTtyY",
      "duration": 5245,
      "start_time": 406208
    },
    {
      "id": "_axXS28dPRI",
      "duration": 5400,
      "start_time": 411453
    },
    {
      "id": "yiIA8lVSCu8",
      "duration": 6150,
      "start_time": 416853
    },
    {
      "id": "uNTgy1l1D8A",
      "duration": 5386,
      "start_time": 423003
    },
    {
      "id": "sJQrURu7l8g",
      "duration": 6479,
      "start_time": 428389
    },
    {
      "id": "EW2EUQM5Yns",
      "duration": 5166,
      "start_time": 434868
    },
    {
      "id": "YPhpiwc94yk",
      "duration": 4839,
      "start_time": 440034
    },
    {
      "id": "6A-pXWRMJRw",
      "duration": 5515,
      "start_time": 444873
    },
    {
      "id": "qx05t1k-yGg",
      "duration": 6025,
      "start_time": 450388
    },
    {
      "id": "lPxmqxzp-o8",
      "duration": 7558,
      "start_time": 456413
    },
    {
      "id": "6pcuIeg-ZRs",
      "duration": 6168,
      "start_time": 463971
    },
    {
      "id": "MwDM-YzjLC8",
      "duration": 5330,
      "start_time": 470139
    },
    {
      "id": "ksQvz1GV9Ts",
      "duration": 5946,
      "start_time": 475469
    },
    {
      "id": "2d6UuXNYP4A",
      "duration": 3552,
      "start_time": 481415
    },
    {
      "id": "BgBXXvgqonk",
      "duration": 5863,
      "start_time": 484967
    },
    {
      "id": "B_iF7Yax99M",
      "duration": 4723,
      "start_time": 490830
    },
    {
      "id": "m0_Fgc6jKp8",
      "duration": 5114,
      "start_time": 495553
    },
    {
      "id": "N9atCS2vPXM",
      "duration": 7184,
      "start_time": 500667
    },
    {
      "id": "cgTZX_Ko0uc",
      "duration": 5737,
      "start_time": 507851
    },
    {
      "id": "-oQgmqL0BZY",
      "duration": 5832,
      "start_time": 513588
    },
    {
      "id": "UMOk-mUKwT8",
      "duration": 6190,
      "start_time": 519420
    },
    {
      "id": "q0jUp9zdiXc",
      "duration": 6687,
      "start_time": 525610
    },
    {
      "id": "dr6Pr6S9eyA",
      "duration": 6086,
      "start_time": 532297
    },
    {
      "id": "4SdRszNR_BA",
      "duration": 6869,
      "start_time": 538383
    },
    {
      "id": "kgcNdOHZW6I",
      "duration": 5045,
      "start_time": 545252
    },
    {
      "id": "NC1OWdulKnk",
      "duration": 6361,
      "start_time": 550297
    },
    {
      "id": "8NrEBj787Xk",
      "duration": 5670,
      "start_time": 556658
    },
    {
      "id": "6ZNkv2HCSt4",
      "duration": 5906,
      "start_time": 562328
    },
    {
      "id": "82t3sQudxvk",
      "duration": 5245,
      "start_time": 568234
    },
    {
      "id": "aVWB032RR0w",
      "duration": 5783,
      "start_time": 573479
    },
    {
      "id": "4-eg-0AzCEE",
      "duration": 5342,
      "start_time": 579262
    },
    {
      "id": "mEmn-msMxew",
      "duration": 6762,
      "start_time": 584604
    },
    {
      "id": "P62zpP56t2Q",
      "duration": 4480,
      "start_time": 591366
    },
    {
      "id": "KFyQpeIgoh0",
      "duration": 6116,
      "start_time": 595846
    },
    {
      "id": "n64WnqhjmwY",
      "duration": 5791,
      "start_time": 601962
    },
    {
      "id": "bE1cxFSpm2s",
      "duration": 5150,
      "start_time": 607753
    },
    {
      "id": "1YTZjgPW_Cw",
      "duration": 5179,
      "start_time": 612903
    },
    {
      "id": "qLL00f6jUxU",
      "duration": 5193,
      "start_time": 618082
    },
    {
      "id": "clYTaPcU0uc",
      "duration": 4781,
      "start_time": 623275
    },
    {
      "id": "ebne5fuqtME",
      "duration": 5286,
      "start_time": 628056
    },
    {
      "id": "EnolLJVvyuU",
      "duration": 4995,
      "start_time": 633342
    },
    {
      "id": "nHyX-Y8fLog",
      "duration": 5411,
      "start_time": 638337
    },
    {
      "id": "lrXeS6qagGY",
      "duration": 5233,
      "start_time": 643748
    },
    {
      "id": "e207GpumJuY",
      "duration": 4538,
      "start_time": 648981
    },
    {
      "id": "Xg0DGJeS5VI",
      "duration": 6878,
      "start_time": 653519
    },
    {
      "id": "y4xDPVRmQVY",
      "duration": 4698,
      "start_time": 660397
    },
    {
      "id": "gz9zXokbE8w",
      "duration": 5638,
      "start_time": 665095
    },
    {
      "id": "4KEV8mu9VAA",
      "duration": 6194,
      "start_time": 670733
    },
    {
      "id": "U82LHpxwhAc",
      "duration": 4897,
      "start_time": 676927
    },
    {
      "id": "L9N_p9WOmRw",
      "duration": 5587,
      "start_time": 681824
    },
    {
      "id": "0mlEQPYCl9g",
      "duration": 5690,
      "start_time": 687411
    },
    {
      "id": "-8ipmx-86Uc",
      "duration": 6005,
      "start_time": 693101
    },
    {
      "id": "kJILFPyczNo",
      "duration": 6432,
      "start_time": 699106
    },
    {
      "id": "nEqypzW2x_E",
      "duration": 5448,
      "start_time": 705538
    },
    {
      "id": "fpXLgYCGIGU",
      "duration": 5092,
      "start_time": 710986
    },
    {
      "id": "F-CNxxwpyTA",
      "duration": 5227,
      "start_time": 716078
    },
    {
      "id": "ubAYmpHBgPM",
      "duration": 4905,
      "start_time": 721305
    },
    {
      "id": "jKFXVzm2LT4",
      "duration": 4472,
      "start_time": 726210
    },
    {
      "id": "xg48xPmyShU",
      "duration": 5378,
      "start_time": 730682
    },
    {
      "id": "VDYVbEk3jus",
      "duration": 3110,
      "start_time": 736060
    },
    {
      "id": "C4nuXpp5B2M",
      "duration": 3503,
      "start_time": 739170
    },
    {
      "id": "XCzPqFrgBYo",
      "duration": 4262,
      "start_time": 742673
    },
    {
      "id": "bBs5Hl6SQDw",
      "duration": 4576,
      "start_time": 746935
    },
    {
      "id": "60YRsdK3Us4",
      "duration": 4545,
      "start_time": 751511
    },
    {
      "id": "stfIxHMj7fA",
      "duration": 3886,
      "start_time": 756056
    },
    {
      "id": "0IMRrsCFj6E",
      "duration": 4704,
      "start_time": 759942
    },
    {
      "id": "0ubZ7eTeBs8",
      "duration": 3748,
      "start_time": 764646
    },
    {
      "id": "vCa3wMMjbsA",
      "duration": 3652,
      "start_time": 768394
    },
    {
      "id": "6Bs7o8ea_NA",
      "duration": 4475,
      "start_time": 772046
    },
    {
      "id": "IeF2A9VVZp0",
      "duration": 4478,
      "start_time": 776521
    },
    {
      "id": "gm2z5JviCcI",
      "duration": 3373,
      "start_time": 780999
    },
    {
      "id": "HQcoI3Q-it8",
      "duration": 4533,
      "start_time": 784372
    },
    {
      "id": "T2YEQRGRTY0",
      "duration": 5009,
      "start_time": 788905
    },
    {
      "id": "5xAnI9AkzrQ",
      "duration": 4186,
      "start_time": 793914
    },
    {
      "id": "Tj_M0i7QqUI",
      "duration": 3461,
      "start_time": 798100
    },
    {
      "id": "LURgEHMHSNY",
      "duration": 3625,
      "start_time": 801561
    },
    {
      "id": "yyV2UtHoDWs",
      "duration": 4205,
      "start_time": 805186
    },
    {
      "id": "RPCy1oWdva4",
      "duration": 3824,
      "start_time": 809391
    },
    {
      "id": "AyGK1FFiK08",
      "duration": 6331,
      "start_time": 813215
    },
    {
      "id": "mhAQoS0mRIw",
      "duration": 3090,
      "start_time": 819546
    },
    {
      "id": "KwzhUFfAAxw",
      "duration": 5011,
      "start_time": 822636
    },
    {
      "id": "jBfM31er-Lw",
      "duration": 3809,
      "start_time": 827647
    },
    {
      "id": "1soF6YOOfYA",
      "duration": 6156,
      "start_time": 831456
    },
    {
      "id": "T80N0qdH18s",
      "duration": 5550,
      "start_time": 837612
    },
    {
      "id": "C4Du7HAdzGU",
      "duration": 4379,
      "start_time": 843162
    },
    {
      "id": "ZBlYK1LnMWA",
      "duration": 5388,
      "start_time": 847541
    },
    {
      "id": "lL7El-YwO3Y",
      "duration": 5304,
      "start_time": 852929
    },
    {
      "id": "59gLDumyufg",
      "duration": 5398,
      "start_time": 858233
    },
    {
      "id": "RBD5vzrXqS8",
      "duration": 4108,
      "start_time": 863631
    },
    {
      "id": "sBgvmX9b2uU",
      "duration": 7845,
      "start_time": 867739
    },
    {
      "id": "2MqrkIW0OuY",
      "duration": 5844,
      "start_time": 875584
    },
    {
      "id": "tEQjqAEXHOQ",
      "duration": 5252,
      "start_time": 881428
    },
    {
      "id": "0esPyw56OUU",
      "duration": 6664,
      "start_time": 886680
    },
    {
      "id": "VSWEd5YC6xw",
      "duration": 4786,
      "start_time": 893344
    },
    {
      "id": "gCrcb7JBgDs",
      "duration": 6864,
      "start_time": 898130
    },
    {
      "id": "Yx1C7erZQkw",
      "duration": 6186,
      "start_time": 904994
    },
    {
      "id": "x-02Cj1O2VE",
      "duration": 5465,
      "start_time": 911180
    },
    {
      "id": "A8yruBUND0Y",
      "duration": 5909,
      "start_time": 916645
    },
    {
      "id": "LydJfCELL6M",
      "duration": 4587,
      "start_time": 922554
    },
    {
      "id": "I0ULqfoKXVk",
      "duration": 5194,
      "start_time": 927141
    },
    {
      "id": "ZtLlA9b9pPM",
      "duration": 4267,
      "start_time": 932335
    },
    {
      "id": "21BOpAA4Krs",
      "duration": 3333,
      "start_time": 936602
    },
    {
      "id": "UUaB7OQsStg",
      "duration": 4535,
      "start_time": 939935
    },
    {
      "id": "Tx0P72zTNBE",
      "duration": 4562,
      "start_time": 944470
    },
    {
      "id": "gsFBavCaYFg",
      "duration": 3738,
      "start_time": 949032
    },
    {
      "id": "WEeqalpLi3A",
      "duration": 4837,
      "start_time": 952770
    },
    {
      "id": "yH2WD5UmL5c",
      "duration": 6180,
      "start_time": 957607
    },
    {
      "id": "iNTE-dQe-R8",
      "duration": 6617,
      "start_time": 963787
    },
    {
      "id": "eV8G2qrw55g",
      "duration": 4720,
      "start_time": 970404
    },
    {
      "id": "uPe5RZ2fUe0",
      "duration": 4253,
      "start_time": 975124
    },
    {
      "id": "kIVo2JGKYLI",
      "duration": 2943,
      "start_time": 979377
    },
    {
      "id": "UIoxLlX4dmw",
      "duration": 4859,
      "start_time": 982320
    },
    {
      "id": "NfX4YqeF2w8",
      "duration": 4015,
      "start_time": 987179
    },
    {
      "id": "hqIdcU_7Uwc",
      "duration": 6028,
      "start_time": 991194
    },
    {
      "id": "hWaiPQO_X5k",
      "duration": 4363,
      "start_time": 997222
    },
    {
      "id": "YH5Abr9Lwkc",
      "duration": 5689,
      "start_time": 1001585
    },
    {
      "id": "VZ9M83hdWi0",
      "duration": 4549,
      "start_time": 1007274
    },
    {
      "id": "KNAfsbvlL5Q",
      "duration": 4265,
      "start_time": 1011823
    },
    {
      "id": "SRb2WsY3mx8",
      "duration": 6896,
      "start_time": 1016088
    },
    {
      "id": "cFUpcD8CsSU",
      "duration": 4929,
      "start_time": 1022984
    },
    {
      "id": "5XxrGIJnPKQ",
      "duration": 4225,
      "start_time": 1027913
    },
    {
      "id": "PRLFfdy1As0",
      "duration": 4116,
      "start_time": 1032138
    },
    {
      "id": "OPU3fWW6b1Y",
      "duration": 5463,
      "start_time": 1036254
    },
    {
      "id": "sQgfm5QozA8",
      "duration": 4442,
      "start_time": 1041717
    },
    {
      "id": "mWR9W1Ssp4Y",
      "duration": 5283,
      "start_time": 1046159
    },
    {
      "id": "ogrVR2C56EI",
      "duration": 5622,
      "start_time": 1051442
    },
    {
      "id": "9b1K4uVt0RM",
      "duration": 4557,
      "start_time": 1057064
    },
    {
      "id": "BDQlKmU3QP8",
      "duration": 5283,
      "start_time": 1061621
    },
    {
      "id": "s5-aJBGxBzw",
      "duration": 5019,
      "start_time": 1066904
    },
    {
      "id": "hWzffoLefYc",
      "duration": 3963,
      "start_time": 1071923
    },
    {
      "id": "X7h1NT0gG7k",
      "duration": 4288,
      "start_time": 1075886
    },
    {
      "id": "Dy603XWJZVo",
      "duration": 4961,
      "start_time": 1080174
    },
    {
      "id": "chMnkae2btc",
      "duration": 5226,
      "start_time": 1085135
    },
    {
      "id": "YzpUouHRGt8",
      "duration": 5064,
      "start_time": 1090361
    },
    {
      "id": "j0sdNuzsaDU",
      "duration": 5956,
      "start_time": 1095425
    },
    {
      "id": "-89gDgAed7k",
      "duration": 5802,
      "start_time": 1101381
    },
    {
      "id": "zVwfLliCac8",
      "duration": 5513,
      "start_time": 1107183
    },
    {
      "id": "dKUMgTQ0xpE",
      "duration": 4460,
      "start_time": 1112696
    },
    {
      "id": "2U8NzEEDKYA",
      "duration": 4215,
      "start_time": 1117156
    },
    {
      "id": "Lwk99IDjWyc",
      "duration": 4070,
      "start_time": 1121371
    },
    {
      "id": "HAO8XO8gDPM",
      "duration": 3383,
      "start_time": 1125441
    },
    {
      "id": "6apvU03PJ-I",
      "duration": 4867,
      "start_time": 1128824
    },
    {
      "id": "8Ms55ww5M8M",
      "duration": 3755,
      "start_time": 1133691
    },
    {
      "id": "-8EJ9uhsfQQ",
      "duration": 6338,
      "start_time": 1137446
    },
    {
      "id": "glVuEvBqlQ0",
      "duration": 6005,
      "start_time": 1143784
    },
    {
      "id": "MNRSxu22NxU",
      "duration": 6102,
      "start_time": 1149789
    },
    {
      "id": "VWzpJTvUG-A",
      "duration": 6660,
      "start_time": 1155891
    },
    {
      "id": "3ZOV4YhquXI",
      "duration": 7373,
      "start_time": 1162551
    },
    {
      "id": "Ueo2TkOkEgs",
      "duration": 5157,
      "start_time": 1169924
    },
    {
      "id": "etsK2YeBm-E",
      "duration": 4017,
      "start_time": 1175081
    },
    {
      "id": "MVXYRYJ6Qs4",
      "duration": 3944,
      "start_time": 1179098
    },
    {
      "id": "WiQFkEM1H00",
      "duration": 7916,
      "start_time": 1183042
    },
    {
      "id": "rRP6qxbUmCg",
      "duration": 5477,
      "start_time": 1190958
    },
    {
      "id": "ixtJ1bTG98k",
      "duration": 4897,
      "start_time": 1196435
    },
    {
      "id": "p0TvUz2a52k",
      "duration": 5093,
      "start_time": 1201332
    },
    {
      "id": "dHsj_tRDzvo",
      "duration": 4487,
      "start_time": 1206425
    },
    {
      "id": "pBYaI1lDMKY",
      "duration": 4448,
      "start_time": 1210912
    },
    {
      "id": "qAB-PNKuNWA",
      "duration": 4331,
      "start_time": 1215360
    },
    {
      "id": "3GV3JgrAbZg",
      "duration": 5194,
      "start_time": 1219691
    },
    {
      "id": "w2onY4GM4HM",
      "duration": 5832,
      "start_time": 1224885
    },
    {
      "id": "tpvglGFNp10",
      "duration": 6096,
      "start_time": 1230717
    },
    {
      "id": "0nBMnu2ACbQ",
      "duration": 6219,
      "start_time": 1236813
    },
    {
      "id": "vWHHcX1IjQ4",
      "duration": 4560,
      "start_time": 1243032
    },
    {
      "id": "JYZb3l0cGR0",
      "duration": 6360,
      "start_time": 1247592
    },
    {
      "id": "hx4YIo8Qwl8",
      "duration": 4887,
      "start_time": 1253952
    },
    {
      "id": "HL2ZV2frNXU",
      "duration": 6414,
      "start_time": 1258839
    },
    {
      "id": "-iOoAiB1Ln0",
      "duration": 6955,
      "start_time": 1265253
    },
    {
      "id": "PgI5mBHbZIo",
      "duration": 6258,
      "start_time": 1272208
    },
    {
      "id": "7AspODjBcLk",
      "duration": 5992,
      "start_time": 1278466
    },
    {
      "id": "Ub0AVfzv9DM",
      "duration": 6050,
      "start_time": 1284458
    },
    {
      "id": "Wdi7PD3dNkY",
      "duration": 5371,
      "start_time": 1290508
    },
    {
      "id": "hGM4Jmkc8iQ",
      "duration": 6044,
      "start_time": 1295879
    },
    {
      "id": "bzowlRE3F6A",
      "duration": 5777,
      "start_time": 1301923
    },
    {
      "id": "CLh9s7lPpKs",
      "duration": 5758,
      "start_time": 1307700
    },
    {
      "id": "L3FLwVfsnAE",
      "duration": 5661,
      "start_time": 1313458
    },
    {
      "id": "aC4ISU1d3Ag",
      "duration": 4798,
      "start_time": 1319119
    },
    {
      "id": "O-x6Pg-DQrY",
      "duration": 4110,
      "start_time": 1323917
    },
    {
      "id": "crbfJ34D0LA",
      "duration": 7280,
      "start_time": 1328027
    },
    {
      "id": "-lSgseNLPyk",
      "duration": 6061,
      "start_time": 1335307
    },
    {
      "id": "uHUdU4efOKI",
      "duration": 5494,
      "start_time": 1341368
    },
    {
      "id": "OQaA95lRqrc",
      "duration": 8056,
      "start_time": 1346862
    },
    {
      "id": "eI4ng_MH-6w",
      "duration": 6251,
      "start_time": 1354918
    },
    {
      "id": "lhaJO-zi3Yk",
      "duration": 5387,
      "start_time": 1361169
    },
    {
      "id": "KnCvn_SI3nk",
      "duration": 5255,
      "start_time": 1366556
    },
    {
      "id": "gzfN7xlz3uo",
      "duration": 5711,
      "start_time": 1371811
    },
    {
      "id": "GKoA79adKgk",
      "duration": 4197,
      "start_time": 1377522
    },
    {
      "id": "G4quVnmuuT4",
      "duration": 10628,
      "start_time": 1381719
    },
    {
      "id": "oHE2zkLZB6k",
      "duration": 5181,
      "start_time": 1392347
    },
    {
      "id": "qmUj_tyoJPk",
      "duration": 5946,
      "start_time": 1397528
    },
    {
      "id": "LaoNx0KuXJ8",
      "duration": 6150,
      "start_time": 1403474
    },
    {
      "id": "eGjPDxqZmfw",
      "duration": 5297,
      "start_time": 1409624
    },
    {
      "id": "gT1pmsnWsso",
      "duration": 5114,
      "start_time": 1414921
    },
    {
      "id": "OLYGhVAlbgY",
      "duration": 3622,
      "start_time": 1420035
    },
    {
      "id": "GYfmVCCfYfM",
      "duration": 6893,
      "start_time": 1423657
    },
    {
      "id": "i6YV7eK-dW0",
      "duration": 5247,
      "start_time": 1430550
    },
    {
      "id": "_h0Kgo3N2fc",
      "duration": 4085,
      "start_time": 1435797
    },
    {
      "id": "Cgcr4dOrrY8",
      "duration": 5649,
      "start_time": 1439882
    },
    {
      "id": "ub-prLnJRtQ",
      "duration": 4012,
      "start_time": 1445531
    },
    {
      "id": "i3U4IQI85Q8",
      "duration": 5303,
      "start_time": 1449543
    },
    {
      "id": "oc-fKMv6vRE",
      "duration": 6123,
      "start_time": 1454846
    },
    {
      "id": "T-dtj9RQI64",
      "duration": 5820,
      "start_time": 1460969
    },
    {
      "id": "h_62QxEBvE8",
      "duration": 2656,
      "start_time": 1466789
    },
    {
      "id": "yuAo77lZ-OQ",
      "duration": 4238,
      "start_time": 1469445
    },
    {
      "id": "e7oqz1aAIPs",
      "duration": 4909,
      "start_time": 1473683
    },
    {
      "id": "lE6ircTo_i4",
      "duration": 3990,
      "start_time": 1478592
    },
    {
      "id": "yk5DscS_vB8",
      "duration": 6012,
      "start_time": 1482582
    },
    {
      "id": "miyh2guoHDM",
      "duration": 5528,
      "start_time": 1488594
    },
    {
      "id": "31o7zHOfrKs",
      "duration": 5032,
      "start_time": 1494122
    },
    {
      "id": "SPRWRa3YKpc",
      "duration": 3725,
      "start_time": 1499154
    },
    {
      "id": "MakhXobfgpY",
      "duration": 4118,
      "start_time": 1502879
    },
    {
      "id": "PP5lauY99OU",
      "duration": 7495,
      "start_time": 1506997
    },
    {
      "id": "H6ovF2zRomA",
      "duration": 5956,
      "start_time": 1514492
    },
    {
      "id": "zhgrIIttGWY",
      "duration": 7047,
      "start_time": 1520448
    },
    {
      "id": "JJQNUdr-aJ8",
      "duration": 5744,
      "start_time": 1527495
    },
    {
      "id": "-7p_Ju3C-jI",
      "duration": 6386,
      "start_time": 1533239
    },
    {
      "id": "eJN0D3u7jkk",
      "duration": 3569,
      "start_time": 1539625
    },
    {
      "id": "sVRj-L1O8sM",
      "duration": 5547,
      "start_time": 1543194
    },
    {
      "id": "N6wrQn9_Pak",
      "duration": 6511,
      "start_time": 1548741
    },
    {
      "id": "3qvEqrKIVSI",
      "duration": 4221,
      "start_time": 1555252
    },
    {
      "id": "gTcZDejv6Xc",
      "duration": 4527,
      "start_time": 1559473
    },
    {
      "id": "yfC54eshig4",
      "duration": 7238,
      "start_time": 1564000
    },
    {
      "id": "72dEfcC13g4",
      "duration": 5037,
      "start_time": 1571238
    },
    {
      "id": "3Bc9YAF-qDg",
      "duration": 5304,
      "start_time": 1576275
    },
    {
      "id": "XtaWk9ScjV8",
      "duration": 5241,
      "start_time": 1581579
    },
    {
      "id": "ApfM2iGTLYY",
      "duration": 5436,
      "start_time": 1586820
    },
    {
      "id": "8_dt3jBVohY",
      "duration": 5644,
      "start_time": 1592256
    },
    {
      "id": "VWuspuIxBaI",
      "duration": 13236,
      "start_time": 1597900
    },
    {
      "id": "gjCKHkKfpLA",
      "duration": 4210,
      "start_time": 1611136
    },
    {
      "id": "wOhAp7TvyfA",
      "duration": 4469,
      "start_time": 1615346
    },
    {
      "id": "abcHT7D2_2Q",
      "duration": 5902,
      "start_time": 1619815
    },
    {
      "id": "pIoB2XwEhWU",
      "duration": 7372,
      "start_time": 1625717
    },
    {
      "id": "D5RWEnzgXMc",
      "duration": 4673,
      "start_time": 1633089
    },
    {
      "id": "lGANB9m7gMI",
      "duration": 4043,
      "start_time": 1637762
    },
    {
      "id": "eT1kRdISthI",
      "duration": 4488,
      "start_time": 1641805
    },
    {
      "id": "-6zAoq8tRfI",
      "duration": 9474,
      "start_time": 1646293
    },
    {
      "id": "zgA8ijcQ5Ys",
      "duration": 4081,
      "start_time": 1655767
    },
    {
      "id": "SiPLTvEGsIk",
      "duration": 9162,
      "start_time": 1659848
    },
    {
      "id": "bG3cBaULu6w",
      "duration": 5708,
      "start_time": 1669010
    },
    {
      "id": "-XN2wjbqC1E",
      "duration": 4016,
      "start_time": 1674718
    },
    {
      "id": "ZwV7gyME3VM",
      "duration": 6492,
      "start_time": 1678734
    },
    {
      "id": "8riPhFdoaJU",
      "duration": 7030,
      "start_time": 1685226
    },
    {
      "id": "2XiNtZJItjE",
      "duration": 7210,
      "start_time": 1692256
    },
    {
      "id": "sit9UJPWRRY",
      "duration": 4494,
      "start_time": 1699466
    },
    {
      "id": "-_5KNUzokp8",
      "duration": 4166,
      "start_time": 1703960
    },
    {
      "id": "pVoQGDhLlaE",
      "duration": 7519,
      "start_time": 1708126
    },
    {
      "id": "xx_92qfIkKc",
      "duration": 6360,
      "start_time": 1715645
    },
    {
      "id": "kK36jw_W4zw",
      "duration": 13016,
      "start_time": 1722005
    },
    {
      "id": "TjrlzAqz-6A",
      "duration": 3899,
      "start_time": 1735021
    },
    {
      "id": "gBQDdr0UwiQ",
      "duration": 5738,
      "start_time": 1738920
    },
    {
      "id": "e1-KZuFcVCU",
      "duration": 4788,
      "start_time": 1744658
    },
    {
      "id": "29Mpy-rAm08",
      "duration": 5476,
      "start_time": 1749446
    },
    {
      "id": "qRjogAfsYkk",
      "duration": 6061,
      "start_time": 1754922
    },
    {
      "id": "A6ZZUVSqb3k",
      "duration": 3930,
      "start_time": 1760983
    },
    {
      "id": "M7LbRPEdNqY",
      "duration": 4117,
      "start_time": 1764913
    },
    {
      "id": "q3b1BJ0XW3Y",
      "duration": 4293,
      "start_time": 1769030
    },
    {
      "id": "m67hvL0XAS4",
      "duration": 4087,
      "start_time": 1773323
    },
    {
      "id": "4qyPOAAga-k",
      "duration": 3732,
      "start_time": 1777410
    },
    {
      "id": "fNA0WGGCr4I",
      "duration": 4429,
      "start_time": 1781142
    },
    {
      "id": "LxFve-IXNuc",
      "duration": 4122,
      "start_time": 1785571
    },
    {
      "id": "2K3nfk3A6eE",
      "duration": 3905,
      "start_time": 1789693
    },
    {
      "id": "mUu-O3Jne7Q",
      "duration": 4151,
      "start_time": 1793598
    },
    {
      "id": "TzRtR1BrTtQ",
      "duration": 4066,
      "start_time": 1797749
    },
    {
      "id": "tPMNQVYaaCY",
      "duration": 3579,
      "start_time": 1801815
    },
    {
      "id": "aUgnyKRZpXY",
      "duration": 4311,
      "start_time": 1805394
    },
    {
      "id": "hZTod1BrWak",
      "duration": 3718,
      "start_time": 1809705
    },
    {
      "id": "_xiE7HxV1xQ",
      "duration": 3359,
      "start_time": 1813423
    },
    {
      "id": "dyzWDwFDS9Q",
      "duration": 6594,
      "start_time": 1816782
    },
    {
      "id": "uiXkIVf73Rw",
      "duration": 3971,
      "start_time": 1823376
    },
    {
      "id": "8eROVRvuX0k",
      "duration": 6170,
      "start_time": 1827347
    },
    {
      "id": "PPM2uhNPU_M",
      "duration": 3134,
      "start_time": 1833517
    },
    {
      "id": "CCUPaahj0MU",
      "duration": 5682,
      "start_time": 1836651
    },
    {
      "id": "sejXBn-KHZk",
      "duration": 3816,
      "start_time": 1842333
    },
    {
      "id": "RSgxOWb9JVg",
      "duration": 4229,
      "start_time": 1846149
    },
    {
      "id": "bCYWULPlq0U",
      "duration": 3529,
      "start_time": 1850378
    },
    {
      "id": "d7G1ZVlqwpU",
      "duration": 4117,
      "start_time": 1853907
    },
    {
      "id": "ptGwSzJoIKs",
      "duration": 3595,
      "start_time": 1858024
    },
    {
      "id": "8ilmj47dFjA",
      "duration": 5304,
      "start_time": 1861619
    },
    {
      "id": "qhVolS-snzE",
      "duration": 5026,
      "start_time": 1866923
    },
    {
      "id": "NzvjYjVDHIY",
      "duration": 6255,
      "start_time": 1871949
    },
    {
      "id": "HVDNZeo-5PA",
      "duration": 5209,
      "start_time": 1878204
    },
    {
      "id": "bcpou1tSJ-w",
      "duration": 4945,
      "start_time": 1883413
    },
    {
      "id": "7IArn6-gNek",
      "duration": 5116,
      "start_time": 1888358
    },
    {
      "id": "bQyMs73lStw",
      "duration": 4656,
      "start_time": 1893474
    },
    {
      "id": "RBL3hfTnJ_8",
      "duration": 4202,
      "start_time": 1898130
    },
    {
      "id": "ogbOU-zn3vY",
      "duration": 4748,
      "start_time": 1902332
    },
    {
      "id": "AgAmR0nwgNk",
      "duration": 5367,
      "start_time": 1907080
    },
    {
      "id": "DfLRUb3AF-Q",
      "duration": 5684,
      "start_time": 1912447
    },
    {
      "id": "SWY-dANy3Kw",
      "duration": 5077,
      "start_time": 1918131
    },
    {
      "id": "q6a_BlvY3OI",
      "duration": 3914,
      "start_time": 1923208
    },
    {
      "id": "BB1kGrdNjSM",
      "duration": 4439,
      "start_time": 1927122
    },
    {
      "id": "xMSrCf_Sj8Q",
      "duration": 5694,
      "start_time": 1931561
    },
    {
      "id": "st8oFULPrFs",
      "duration": 4522,
      "start_time": 1937255
    },
    {
      "id": "l_wk74NbZVA",
      "duration": 5387,
      "start_time": 1941777
    },
    {
      "id": "SU2_S8hfWL8",
      "duration": 4155,
      "start_time": 1947164
    },
    {
      "id": "YeSn1aZU6uY",
      "duration": 4522,
      "start_time": 1951319
    },
    {
      "id": "UyNWpRY5lH8",
      "duration": 4610,
      "start_time": 1955841
    },
    {
      "id": "1PTrcre3AcU",
      "duration": 4494,
      "start_time": 1960451
    },
    {
      "id": "nCSYrah0tnM",
      "duration": 3301,
      "start_time": 1964945
    },
    {
      "id": "LHKwDd9mRlU",
      "duration": 4470,
      "start_time": 1968246
    },
    {
      "id": "TVwsuDDhYF8",
      "duration": 3938,
      "start_time": 1972716
    },
    {
      "id": "AYnNJdceVdM",
      "duration": 4883,
      "start_time": 1976654
    },
    {
      "id": "bdk55Bxjc18",
      "duration": 4844,
      "start_time": 1981537
    },
    {
      "id": "ZMjMYRkMH6w",
      "duration": 6708,
      "start_time": 1986381
    },
    {
      "id": "SMYknkIn60E",
      "duration": 4926,
      "start_time": 1993089
    },
    {
      "id": "GWGLmG9T_hA",
      "duration": 5433,
      "start_time": 1998015
    },
    {
      "id": "HnDGF0EZufA",
      "duration": 4177,
      "start_time": 2003448
    },
    {
      "id": "i-K2KKLPdo0",
      "duration": 6030,
      "start_time": 2007625
    },
    {
      "id": "8PNI6IjsHws",
      "duration": 4110,
      "start_time": 2013655
    },
    {
      "id": "ccKgn3w12CU",
      "duration": 4656,
      "start_time": 2017765
    },
    {
      "id": "QhJ6q1vOwWI",
      "duration": 5222,
      "start_time": 2022421
    },
    {
      "id": "c7fPuwLEz6M",
      "duration": 6344,
      "start_time": 2027643
    },
    {
      "id": "P-fl9RdQ22s",
      "duration": 5578,
      "start_time": 2033987
    },
    {
      "id": "WPuOTlGA8j8",
      "duration": 5718,
      "start_time": 2039565
    },
    {
      "id": "x4gUhsgWbPU",
      "duration": 5413,
      "start_time": 2045283
    },
    {
      "id": "Olc_LYdAMF4",
      "duration": 5204,
      "start_time": 2050696
    },
    {
      "id": "1HAk9N0KTK4",
      "duration": 5312,
      "start_time": 2055900
    },
    {
      "id": "RhMkt-NW6AQ",
      "duration": 5900,
      "start_time": 2061212
    },
    {
      "id": "SmS2d5cLjUk",
      "duration": 6342,
      "start_time": 2067112
    },
    {
      "id": "NySIyvdNIlY",
      "duration": 3601,
      "start_time": 2073454
    },
    {
      "id": "oJz8Bss7G9g",
      "duration": 5282,
      "start_time": 2077055
    },
    {
      "id": "x4LmnvzrI-Q",
      "duration": 6342,
      "start_time": 2082337
    },
    {
      "id": "MaWPQtobB3A",
      "duration": 5114,
      "start_time": 2088679
    },
    {
      "id": "5ywn9GHgoCg",
      "duration": 4940,
      "start_time": 2093793
    },
    {
      "id": "TmVHWitB48k",
      "duration": 5943,
      "start_time": 2098733
    },
    {
      "id": "LYGzxPPD3FI",
      "duration": 4288,
      "start_time": 2104676
    },
    {
      "id": "YgLYpBcbZc8",
      "duration": 6041,
      "start_time": 2108964
    },
    {
      "id": "sUj0X1Xl4aQ",
      "duration": 6671,
      "start_time": 2115005
    },
    {
      "id": "skWCeP1NV4k",
      "duration": 5977,
      "start_time": 2121676
    },
    {
      "id": "k8LTp3XfxO8",
      "duration": 7332,
      "start_time": 2127653
    }
  ]
}